dcoraid/__init__.py
dcoraid/__main__.py
dcoraid/_version.py
dcoraid/cli.py
dcoraid/common.py
dcoraid/loggers.py
dcoraid/api/__init__.py
dcoraid/api/ckan_api.py
dcoraid/api/dataset.py
dcoraid/api/errors.py
dcoraid/api/s3_api.py
dcoraid/dbmodel/__init__.py
dcoraid/dbmodel/db_api.py
dcoraid/dbmodel/db_core.py
dcoraid/dbmodel/extract.py
dcoraid/download/__init__.py
dcoraid/download/job.py
dcoraid/download/queue.py
dcoraid/download/task.py
dcoraid/gui/__init__.py
dcoraid/gui/api.py
dcoraid/gui/main.py
dcoraid/gui/main.ui
dcoraid/gui/status_widget.py
dcoraid/gui/updater.py
dcoraid/gui/browse_public/__init__.py
dcoraid/gui/browse_public/widget_browse_public.py
dcoraid/gui/browse_public/widget_browse_public.ui
dcoraid/gui/dbview/__init__.py
dcoraid/gui/dbview/drag_table_widget.py
dcoraid/gui/dbview/filter_base.py
dcoraid/gui/dbview/filter_base.ui
dcoraid/gui/dbview/filter_chain.py
dcoraid/gui/dbview/filter_chain.ui
dcoraid/gui/dbview/filter_views.py
dcoraid/gui/download/__init__.py
dcoraid/gui/download/widget_download.py
dcoraid/gui/download/widget_download.ui
dcoraid/gui/logs/__init__.py
dcoraid/gui/logs/widget_log.py
dcoraid/gui/logs/widget_log.ui
dcoraid/gui/maintenance/__init__.py
dcoraid/gui/maintenance/widget_maintenance.py
dcoraid/gui/maintenance/widget_maintenance.ui
dcoraid/gui/preferences/__init__.py
dcoraid/gui/preferences/dlg_preferences.py
dcoraid/gui/preferences/dlg_preferences.ui
dcoraid/gui/tools/__init__.py
dcoraid/gui/tools/wait_cursor.py
dcoraid/gui/upload/__init__.py
dcoraid/gui/upload/circle_mgr.py
dcoraid/gui/upload/dlg_upload.py
dcoraid/gui/upload/dlg_upload.ui
dcoraid/gui/upload/resource_schema_preset.py
dcoraid/gui/upload/resources_model.py
dcoraid/gui/upload/widget_schema.py
dcoraid/gui/upload/widget_supplement_item.py
dcoraid/gui/upload/widget_supplement_item.ui
dcoraid/gui/upload/widget_supplement_tags.ui
dcoraid/gui/upload/widget_tablecell_actions.py
dcoraid/gui/upload/widget_tablecell_actions.ui
dcoraid/gui/upload/widget_upload.py
dcoraid-1.16.11.dist-info/licenses/LICENSE
dcoraid-1.16.11.dist-info/METADATA
dcoraid-1.16.11.dist-info/WHEEL
dcoraid-1.16.11.dist-info/entry_points.txt
dcoraid-1.16.11.dist-info/top_level.txt
dcoraid-1.16.11.dist-info/RECORD
