Metadata-Version: 2.4
Name: dcoraid
Version: 1.16.11
Summary: GUI/CLI for managing data on DCOR
Author: Paul Müller
Maintainer-email: Paul Müller <dev@craban.de>
License-Expression: GPL-3.0-or-later
Project-URL: source, https://github.com/DCOR-dev/DCOR-Aid
Project-URL: tracker, https://github.com/DCOR-dev/DCOR-Aid/issues
Project-URL: documentation, https://dc.readthedocs.io
Project-URL: changelog, https://github.com/DCOR-dev/DCOR-Aid/blob/master/CHANGELOG
Keywords: RT-DC,DC,deformability,cytometry
Classifier: Operating System :: OS Independent
Classifier: Programming Language :: Python :: 3
Classifier: Intended Audience :: Science/Research
Requires-Python: <4,>=3.10
License-File: LICENSE
Requires-Dist: dclab[dcor]>=0.62.11
Requires-Dist: numpy>=1.21
Requires-Dist: requests>=2.31
Requires-Dist: urllib3>=2.0
Requires-Dist: requests_cache
Requires-Dist: requests_toolbelt>=1.0.0
Provides-Extra: gui
Requires-Dist: pyqt5; extra == "gui"
Dynamic: license-file
